saber_shad/__init__.py
saber_shad/api.py
saber_shad/client.py
saber_shad/crypto.py
saber_shad/network.py
saber_shad/utils.py
shad_saber-0.2.0.dist-info/licenses/LICENSE
shad_saber-0.2.0.dist-info/METADATA
shad_saber-0.2.0.dist-info/WHEEL
shad_saber-0.2.0.dist-info/top_level.txt
shad_saber-0.2.0.dist-info/RECORD
